LICENSE
README.md
fast_tmp/__init__.py
fast_tmp/admin/__init__.py
fast_tmp/admin/depends.py
fast_tmp/admin/endpoint.py
fast_tmp/admin/exception_handlers.py
fast_tmp/admin/register.py
fast_tmp/admin/server.py
fast_tmp/admin/site.py
fast_tmp/admin/template.py
fast_tmp/admin/templates/base.html
fast_tmp/admin/templates/index.html
fast_tmp/admin/templates/login.html
fast_tmp/amis/__init__.py
fast_tmp/amis/actions.py
fast_tmp/amis/base.py
fast_tmp/amis/column.py
fast_tmp/amis/crud.py
fast_tmp/amis/enums.py
fast_tmp/amis/formitem.py
fast_tmp/amis/forms/__init__.py
fast_tmp/amis/frame.py
fast_tmp/amis/grid.py
fast_tmp/amis/nav.py
fast_tmp/amis/page.py
fast_tmp/amis/response.py
fast_tmp/amis/style.py
fast_tmp/amis/validate.py
fast_tmp/amis/view/__init__.py
fast_tmp/amis/view/card.py
fast_tmp/amis/view/chart.py
fast_tmp/amis/view/divider.py
fast_tmp/amis/view/table.py
fast_tmp/amis/wizard.py
fast_tmp/conf/__init__.py
fast_tmp/contrib/__init__.py
fast_tmp/contrib/auth/__init__.py
fast_tmp/contrib/auth/hashers.py
fast_tmp/contrib/pydantic/__init__.py
fast_tmp/contrib/tortoise/__init__.py
fast_tmp/contrib/tortoise/fields.py
fast_tmp/contrib/tortoise/validators.py
fast_tmp/exceptions.py
fast_tmp/factory.py
fast_tmp/jinja_extension/__init__.py
fast_tmp/jinja_extension/tags.py
fast_tmp/models.py
fast_tmp/responses.py
fast_tmp/site/__init__.py
fast_tmp/site/base.py
fast_tmp/site/field.py
fast_tmp/site/filter.py
fast_tmp/utils/__init__.py
fast_tmp/utils/crypto.py
fast_tmp/utils/db.py
fast_tmp/utils/encoding.py
fast_tmp/utils/model.py
fast_tmp/utils/token.py
fast_tmp_cli/__init__.py
fast_tmp_cli/tpl/project/cookiecutter.json
fast_tmp_cli/tpl/project/{{cookiecutter.project_slug}}/.env
fast_tmp_cli/tpl/project/{{cookiecutter.project_slug}}/app.py
fast_tmp_cli/tpl/project/{{cookiecutter.project_slug}}/conftest.py
fast_tmp_cli/tpl/project/{{cookiecutter.project_slug}}/static/css/fontawesome.min.css
fast_tmp_cli/tpl/project/{{cookiecutter.project_slug}}/static/css/main.css
fast_tmp-1.1.19.dist-info/LICENSE
fast_tmp-1.1.19.dist-info/METADATA
fast_tmp-1.1.19.dist-info/WHEEL
fast_tmp-1.1.19.dist-info/entry_points.txt
fast_tmp-1.1.19.dist-info/RECORD
