Metadata-Version: 2.1
Name: fast-tmp
Version: 1.1.19
Summary: fastapi tortoise amis admin
Home-page: https://github.com/Chise1/fast-tmp
License: Apache-2.0
Author: Chise1
Author-email: chise123@live.com
Requires-Python: >=3.8,<4.0
Classifier: License :: OSI Approved :: Apache Software License
Classifier: Programming Language :: Python :: 3
Classifier: Programming Language :: Python :: 3.8
Classifier: Programming Language :: Python :: 3.9
Classifier: Programming Language :: Python :: 3.10
Classifier: Programming Language :: Python :: 3.11
Requires-Dist: asgiref (>=3.5.2,<4.0.0)
Requires-Dist: fastapi (>=0.95.0,<0.96.0)
Requires-Dist: python-dotenv (>=1.0.0,<2.0.0)
Requires-Dist: python-jose (>=3.3.0,<4.0.0)
Requires-Dist: python-multipart (>=0.0.6,<0.0.7)
Requires-Dist: toml (>=0.10.2,<0.11.0)
Requires-Dist: tortoise-orm (>=0.19.2,<0.20.0)
Requires-Dist: typer (>=0.7.0,<0.8.0)
Project-URL: Repository, https://github.com/Chise1/fast-tmp
